{
  "name": "datagen_transactions_source_connector_0",
  "config": {
    "connector.class": "io.confluent.kafka.connect.datagen.DatagenConnector",
    "kafka.topic": "transactions",
    "quickstart": "transactions",
    "key.converter": "org.apache.kafka.connect.storage.StringConverter",
    "value.converter": "org.apache.kafka.connect.json.JsonConverter",
    "value.converter.schemas.enable": "true",
    "key.converter.schemas.enable": "false",
    "max.interval": 1000,
    "tasks.max": "1"
  }
}
